{
  "$schema": "./CookieBannerRuleList.schema.json",
  "data": [
    {
      "click": {
        "optIn": "button.btn-accept",
        "presence": "div#gdpr-new-container"
      },
      "domain": "aliexpress.com",
      "cookies": {},
      "id": "80851a39-2183-49e4-99f4-16d6189bff1e"
    },
    {
      "click": {
        "optIn": "button#onetrust-accept-btn-handler",
        "presence": "div#onetrust-consent-sdk"
      },
      "domain": "soundcloud.com",
      "cookies": {},
      "id": "6c7366a0-4762-47b9-8eeb-04e86cc7a0cc"
    },
    {
      "click": {
        "optIn": ".a8c-cookie-banner-accept-all-button",
        "presence": "div.a8c-cookie-banner"
      },
      "domain": "gravatar.com",
      "cookies": {},
      "id": "4b835605-77e0-457a-8409-8d499ee1131c"
    },
    {
      "click": {
        "optIn": "button#onetrust-accept-btn-handler",
        "presence": "div#onetrust-banner-sdk"
      },
      "domain": "fastly.com",
      "cookies": {},
      "id": "c63efcc1-06e0-42c5-955f-f5a61fd0baa2"
    },
    {
      "click": {
        "presence": "div#uhfCookieAlert"
      },
      "domain": "skype.com",
      "cookies": {},
      "id": "0c43a914-8bc7-4872-89f2-f1ad213d2a7f"
    },
    {
      "click": {
        "optIn": ".acceptAll",
        "optOut": ".rejectAll",
        "presence": "div.truste_box_overlay_inner"
      },
      "domain": "flickr.com",
      "cookies": {},
      "id": "22d33421-6872-41bc-9316-adba6a9af18e"
    },
    {
      "click": {
        "optIn": ".cck-actions div > button",
        "optOut": ".cck-actions div > button + button",
        "presence": "div#cookie-consent-banner"
      },
      "domain": "europa.eu",
      "cookies": {},
      "id": "0c74749a-8c53-4bb0-b31a-ab2f89b7f493"
    },
    {
      "click": {
        "optIn": "button#onetrust-accept-btn-handler",
        "presence": "div#onetrust-banner-sdk"
      },
      "domain": "spotify.com",
      "cookies": {},
      "id": "443c2cd7-1d4f-486f-a263-02d57aa70cb3"
    },
    {
      "click": {
        "optOut": "button.cookieBarButtons",
        "presence": "div#cookieBar"
      },
      "domain": "google-analytics.com",
      "cookies": {},
      "id": "286028cd-7cb7-4c71-91a7-ae1a23df8a31"
    },
    {
      "click": {
        "optIn": ".evidon-banner-acceptbutton",
        "optOut": ".evidon-banner-declinebutton",
        "presence": "div.evidon-banner"
      },
      "domain": "dropbox.com",
      "cookies": {},
      "id": "7f82a27a-eaf8-4c16-b15e-66b5efe62fa2"
    },
    {
      "click": {
        "optIn": ".cmpboxbtnyes",
        "optOut": ".cmpboxbtnno",
        "presence": "div#cmpbox"
      },
      "domain": "mail.ru",
      "cookies": {},
      "id": "77424a06-c47f-4b06-9925-e4d5afc7c61a"
    },
    {
      "click": {
        "optIn": "div.uiLayer div > button[type=submit]",
        "optOut": "div.uiLayer div > button + button[type=submit]",
        "presence": "div#cookie-banner"
      },
      "domain": "azure.microsoft.com",
      "cookies": {},
      "id": "f899d35e-20af-4cfb-9856-143a80b86ba9"
    },
    {
      "click": {
        "optIn": ".js-accept-cookies",
        "presence": ".js-consent-banner"
      },
      "domain": "askubuntu.com",
      "cookies": {},
      "id": "71443ce9-15b8-4e07-b51b-1f2158521ea9"
    },
    {
      "click": {
        "optIn": ".js-accept-cookies",
        "presence": ".js-consent-banner"
      },
      "domain": "serverfault.com",
      "cookies": {},
      "id": "98fcaf1f-aae9-4fb4-985a-e4f7230c3fdb"
    },
    {
      "click": {
        "optIn": ".js-accept-cookies",
        "presence": ".js-consent-banner"
      },
      "domain": "stackexchange.com",
      "cookies": {},
      "id": "6dca720b-4df0-4707-86c8-2a98748cba02"
    },
    {
      "click": {
        "optIn": ".js-accept-cookies",
        "presence": ".js-consent-banner"
      },
      "domain": "stackoverflow.com",
      "cookies": {},
      "id": "05e86dab-14e2-4fbe-9229-539752d57f8f"
    },
    {
      "click": {
        "hide": "div#onetrust-consent-sdk",
        "optIn": "button#onetrust-accept-btn-handler",
        "optOut": "button#onetrust-reject-all-handler",
        "presence": "div#onetrust-banner-sdk"
      },
      "domain": "cnn.com",
      "cookies": {},
      "id": "3dde4bbf-a1fa-458d-afb1-e2ae5f459217"
    },
    {
      "click": {
        "optIn": "button.sp_choice_type_11",
        "presence": "body"
      },
      "domain": "privacy-mgmt.com",
      "cookies": {},
      "id": "d3d9bf51-2613-408a-afad-5d203fea7857"
    },
    {
      "click": {},
      "domain": "youtube.com",
      "cookies": {
        "optOut": [
          {
            "name": "CONSENT",
            "path": "/",
            "value": "PENDING",
            "sameSite": 0
          },
          {
            "name": "SOCS",
            "path": "/",
            "value": "CAESEwgDEgk0Njk1NTcxMzUaAmVuIAEaBgiA1JWYBg",
            "sameSite": 0
          }
        ]
      },
      "id": "788ed05e-cf93-41a8-b2e5-c5571d855232"
    },
    {
      "click": {
        "hide": "#onetrust-consent-sdk",
        "optIn": "#accept-recommended-btn-handler",
        "optOut": "button.save-preference-btn-handler",
        "presence": "#onetrust-pc-sdk"
      },
      "domain": "dhl.com",
      "cookies": {},
      "id": "a224a333-229d-4f1f-af68-41a25a152037"
    },
    {
      "click": {
        "optIn": "button#L2AGLb",
        "optOut": "button#W0wltc",
        "presence": "div.spoKVd"
      },
      "domain": "google.com",
      "cookies": {
        "optOut": [
          {
            "name": "CONSENT",
            "path": "/",
            "value": "PENDING",
            "sameSite": 0
          },
          {
            "name": "SOCS",
            "path": "/",
            "value": "CAESHAgBEhJnd3NfMjAyMjA4MTEtMF9SQzMaAmRlIAEaBgiA1JWYBg",
            "sameSite": 0
          }
        ]
      },
      "id": "ffe76ba2-d6aa-47f4-ab85-9368feeb4519"
    },
    {
      "click": {
        "optIn": "button#L2AGLb",
        "optOut": "button#W0wltc",
        "presence": "div.spoKVd"
      },
      "domain": "google.fr",
      "cookies": {
        "optOut": [
          {
            "name": "CONSENT",
            "path": "/",
            "value": "PENDING",
            "sameSite": 0
          },
          {
            "name": "SOCS",
            "path": "/",
            "value": "CAESHAgBEhJnd3NfMjAyMjA4MTEtMF9SQzMaAmRlIAEaBgiA1JWYBg",
            "sameSite": 0
          }
        ]
      },
      "id": "114dde58-155f-45f6-9da6-b545f8f3f613"
    },
    {
      "click": {
        "optIn": "button#L2AGLb",
        "optOut": "button#W0wltc",
        "presence": "div.spoKVd"
      },
      "domain": "google.de",
      "cookies": {
        "optOut": [
          {
            "name": "CONSENT",
            "path": "/",
            "value": "PENDING",
            "sameSite": 0
          },
          {
            "name": "SOCS",
            "path": "/",
            "value": "CAESHAgBEhJnd3NfMjAyMjA4MTEtMF9SQzMaAmRlIAEaBgiA1JWYBg",
            "sameSite": 0
          }
        ]
      },
      "id": "01c11d97-981e-4543-ae60-e468f1adbe98"
    },
    {
      "click": {
        "optIn": "div.uiLayer div > button + button[type=submit]",
        "optOut": "div.uiLayer div > button[type=submit]",
        "presence": "div.uiLayer"
      },
      "domain": "facebook.com",
      "cookies": {},
      "id": "d1d8ba36-ced7-4453-8b17-2e051e0ab1eb"
    },
    {
      "click": {
        "optIn": "div#uhfCookieAlert div > button",
        "optOut": "iv#uhfCookieAlert div > button + button",
        "presence": "div#uhfCookieAlert"
      },
      "domain": "microsoft.com",
      "cookies": {},
      "id": "caf8d44d-af29-47a9-aa66-ec4041655d33"
    },
    {
      "click": {
        "optIn": "div#layers div[role]",
        "optOut": "div#layers div[role] + div[role]",
        "presence": "div#layers > div > div > div > div > div"
      },
      "domain": "twitter.com",
      "cookies": {},
      "id": "05b3b417-c4c7-4ed0-a3cf-43053e8b33ab"
    },
    {
      "click": {
        "optIn": "div.global-alert-banner button[action-type=ACCEPT]",
        "optOut": "div.global-alert-banner button[action-type=DENY]",
        "presence": "div.global-alert-banner"
      },
      "domain": "linkedin.com",
      "cookies": {},
      "id": "f1ddc6f6-8927-4205-8003-1f6e84ae22b0"
    },
    {
      "click": {
        "hide": "div#onetrust-consent-sdk",
        "optIn": "button#onetrust-accept-btn-handler",
        "optOut": "button#onetrust-reject-all-handler",
        "presence": "div#onetrust-banner-sdk"
      },
      "domain": "vimeo.com",
      "cookies": {},
      "id": "dd0c1047-7dfa-4ad7-b249-3559e6a466f9"
    },
    {
      "click": {
        "optIn": "button#gdpr-banner-accept",
        "optOut": "button#gdpr-banner-decline",
        "presence": "div#gdpr-banner"
      },
      "domain": "ebay.com",
      "cookies": {},
      "id": "1e6d35e7-b907-4f5c-a09a-9f3336ef6e61"
    },
    {
      "click": {
        "optIn": "button#gdpr-banner-accept",
        "optOut": "button#gdpr-banner-decline",
        "presence": "div#gdpr-banner"
      },
      "domain": "ebay.de",
      "cookies": {},
      "id": "d0356a58-6b55-4bbc-ab79-9ded68601af2"
    },
    {
      "click": {
        "optIn": "button[data-a-target=consent-banner-accept]",
        "presence": "div.consent-banner"
      },
      "domain": "twitch.tv",
      "cookies": {},
      "id": "542aafba-9f44-4321-88e5-ece333073360"
    },
    {
      "click": {
        "optIn": "div.gdpr div > button:not([aria-label]",
        "optOut": "div.gdpr div > button + button:not([aria-label])",
        "presence": "div.gdpr"
      },
      "domain": "nytimes.com",
      "cookies": {
        "optOut": [
          {
            "name": "purr-pref-agent",
            "value": "<Go"
          }
        ]
      },
      "id": "488f07f9-0a01-4118-aab3-2b817e9fe6dc"
    },
    {
      "click": {
        "hide": "div#onetrust-consent-sdk",
        "optIn": "button#onetrust-accept-btn-handler",
        "optOut": "button.ot-pc-refuse-all-handler",
        "presence": "div#onetrust-banner-sdk"
      },
      "domain": "getpocket.com",
      "cookies": {
        "optOut": [
          {
            "name": "OptanonAlertBoxClosed",
            "value": "2022-08-09T16:49:23.845Z"
          }
        ]
      },
      "id": "c2f6b05e-73dc-4df4-bb54-68215bb9f176"
    },
    {
      "click": {
        "optIn": "button#truste-consent-button",
        "presence": "div#truste-consent-track"
      },
      "domain": "forbes.com",
      "cookies": {},
      "id": "30293090-f064-473a-ae0f-cd390507c1c7"
    },
    {
      "click": {
        "optIn": "input#sp-cc-accept[data-cel-widget]",
        "presence": "form#sp-cc"
      },
      "domain": "amazon.de",
      "cookies": {},
      "id": "7957b964-6cc5-4d33-9200-aa35e649a2af"
    },
    {
      "click": {
        "optIn": "button.btn-accept",
        "optOut": "button.btn-reject",
        "presence": "div#cookie-disclosure"
      },
      "domain": "netflix.com",
      "cookies": {},
      "id": "6037802d-9a37-4df2-bf35-9ad60c478725"
    },
    {
      "click": {
        "optIn": "div[role=dialog] > div > button",
        "optOut": "div[role=dialog] > div > button + button",
        "presence": "#scrollview + div"
      },
      "domain": "instagram.com",
      "cookies": {},
      "id": "e7112653-2ab3-4ddf-b0b1-396052c2f001"
    },
    {
      "click": {},
      "domain": "bbc.com",
      "cookies": {
        "optOut": [
          {
            "name": "ckns_explicit",
            "value": "2"
          },
          {
            "name": "ckns_policy",
            "value": "000"
          },
          {
            "name": "ckns_privacy",
            "value": "july2019"
          }
        ]
      },
      "id": "e9a07bcd-28b5-4034-a663-c017e6a8208e"
    },
    {
      "click": {},
      "domain": "bbc.co.uk",
      "cookies": {
        "optOut": [
          {
            "name": "ckns_explicit",
            "value": "2"
          },
          {
            "name": "ckns_policy",
            "value": "000"
          },
          {
            "name": "ckns_privacy",
            "value": "july2019"
          }
        ]
      },
      "id": "1be89e75-e68b-4323-928e-3839995f2be3"
    },
    {
      "click": {},
      "domain": "web.de",
      "cookies": {
        "optOut": [
          {
            "name": "consentLevel",
            "value": "1"
          },
          {
            "name": "euconsent-bypass",
            "value": "1"
          }
        ]
      },
      "id": "290db348-ced2-4f16-9954-da476d0aef01"
    },
    {
      "click": {},
      "domain": "bundesregierung.de",
      "cookies": {
        "optOut": [
          {
            "name": "cookie-allow-necessary",
            "value": "1"
          },
          {
            "name": "cookie-allow-tracking",
            "value": "0"
          },
          {
            "name": "cookie-banner",
            "value": "hide"
          }
        ]
      },
      "id": "84f68b1a-18a2-478c-bc8e-9ec32d4e3e80"
    },
    {
      "click": {},
      "domain": "bing.com",
      "cookies": {
        "optOut": [
          {
            "name": "BCP",
            "value": "AD=0&AL=0&SM=0"
          }
        ]
      },
      "id": "31dc6160-3495-4f4e-8c67-594527bd4051"
    },
    {
      "click": {},
      "domain": "paypal.com",
      "cookies": {
        "optOut": [
          {
            "name": "cookie_prefs",
            "value": "T%3D0%2CP%3D0%2CF%3D0%2Ctype%3Dexplicit_banner"
          }
        ]
      },
      "id": "3f1e21e7-327f-42de-ac40-25da7f4fa7c9"
    },
    {
      "click": {},
      "domain": "mydealz.de",
      "cookies": {
        "optOut": [
          {
            "name": "cookie_policy_agreement",
            "value": "3"
          },
          {
            "name": "dont-track",
            "value": "1"
          }
        ]
      },
      "id": "069f4d94-8031-4b83-b8f9-89752c5c1353"
    },
    {
      "click": {},
      "domain": "whatsapp.com",
      "cookies": {
        "optIn": [
          {
            "name": "wa_cb",
            "value": "1_2022_08_09_"
          }
        ],
        "optOut": []
      },
      "id": "0f4b1486-7d4b-4f73-8ec9-122daca9ebf4"
    },
    {
      "click": {},
      "domain": "wordpress.com",
      "cookies": {
        "optIn": [
          {
            "name": "sensitive_pixel_option",
            "value": "yes"
          }
        ]
      },
      "id": "709f87b8-b010-4d32-b32d-3f265963c6a5"
    },
    {
      "click": {},
      "domain": "bitly.com",
      "cookies": {
        "optIn": [
          {
            "name": "cookie_banner",
            "value": "1"
          }
        ]
      },
      "id": "84a097a3-5cd1-448a-afcf-4be950bc5756"
    },
    {
      "click": {},
      "domain": "yandex.com",
      "cookies": {
        "optOut": [
          {
            "name": "gdpr",
            "value": "1"
          }
        ]
      },
      "id": "37319f5d-9484-4da8-aee1-570a78688da3"
    },
    {
      "click": {},
      "domain": "yandex.ru",
      "cookies": {
        "optOut": [
          {
            "name": "gdpr",
            "value": "1"
          }
        ]
      },
      "id": "128c2e2e-99c8-4f15-9843-dab9942421b0"
    },
    {
      "click": {},
      "domain": "tumblr.com",
      "cookies": {
        "optOut": [
          {
            "name": "euconsent-v2",
            "value": "1"
          },
          {
            "name": "euconsent-v2-noniab",
            "value": "AAYA"
          }
        ]
      },
      "id": "e8f941e6-ac56-4dec-b682-a75e8bd52aae"
    },
    {
      "click": {},
      "domain": "tiktok.com",
      "cookies": {
        "optOut": [
          {
            "name": "cookie-consent",
            "value": "{%22ga%22:false%2C%22af%22:false%2C%22fbp%22:false%2C%22lip%22:false%2C%22bing%22:false%2C%22ttads%22:false%2C%22reddit%22:false%2C%22version%22:%22v8%22}"
          }
        ]
      },
      "id": "d9166ae8-dcc7-4ca2-8b02-0884fb1d6f70"
    },
    {
      "click": {},
      "domain": "reddit.com",
      "cookies": {
        "optOut": [
          {
            "name": "eu_cookie",
            "value": "{%22opted%22:true%2C%22nonessential%22:false}"
          }
        ]
      },
      "id": "c5243e7c-eb86-4a9d-947c-7129e99fbd72"
    },
    {
      "click": {
        "optIn": "button#onetrust-accept-btn-handler",
        "optOut": "button#onetrust-reject-all-handler",
        "presence": "div#onetrust-consent-sdk"
      },
      "domain": "cloudflare.com",
      "cookies": {},
      "id": "0b42c238-b54d-4106-8d9a-81df5bc0b3ae"
    },
    {
      "click": {
        "optIn": "button#L2AGLb",
        "optOut": "button#W0wltc",
        "presence": "div#CXQnmb"
      },
      "domain": "google.com.hk",
      "cookies": {
        "optIn": [
          {
            "name": "SOCS",
            "value": "CAISHAgBEhJnd3NfMjAyMjEwMDYtMF9SQzMaAnJvIAEaBgiAqp2aBg",
            "isSecure": true
          },
          {
            "name": "CONSENT",
            "value": "PENDING"
          }
        ],
        "optOut": [
          {
            "name": "SOCS",
            "value": "CAESHAgBEhJnd3NfMjAyMjEwMDYtMF9SQzMaAnJvIAEaBgiAqp2aBg",
            "isSecure": true
          }
        ]
      },
      "id": "4a947309-9a90-45bc-916c-b76bcd61bed1"
    },
    {
      "click": {
        "optIn": "button#onetrust-accept-btn-handler",
        "optOut": "button#onetrust-reject-all-handler",
        "presence": "div#onetrust-consent-sdk"
      },
      "domain": "msn.com",
      "cookies": {
        "optIn": [
          {
            "name": "eupubconsent-v2",
            "value": "CPg0HlKPg0HlKAcABBENCFCsAP_AAEPAACiQImtf_X__b3_j-_5_f_t0eY1P9_7_v-0zjhedt-8N3d_X_L8X52M7vF36pq4KuR4Eu3LBAQdlHOHcTUmw6IkVqzPsbk2cr7NKJ7PEmnMbO2dYGH9_n93TuZKY7______z_v-v_v____f__-3_3__5_1---wAAB8gdzLv9____393P___9v-_9_____-CIYBJhqXkAXZljgybRpVCiBGFYSHQCgAooBhaIrCB1cFOyuAn1BCwAQCpCcCIEGIKMGAQACCQBIREBIAeCARAEQCAAEAKsBCAAjYBBYAWBgEAAoBoWIEUAQgSEGRwVHKYEBUi0UE9lYglB3saYQhlnARQIAAABABrNECwMhIWDmOAJAS8WSB5ihfIBAaBCAFYALgAhgBkADLAGyAOwAfgBAACCgEYAKeAVeAtAC0gGsAN4AdUA-QCHQEVAJEATYAnYBSIC5AGEgMPAYwAycBnIDPAGfAPwDACgBzAHUASEAkUBkYDdAHEgOzAe6BD4QALABIAOYA3gCQgEigN0AcSA7MB7oD7AIfCIDQAVgBDADIAGWANkAdgA_ACAAEYAKeAVcA1gB1QD5AIdASIAmwBOwCkQFyAMJAYeAycBnIDPgH4CoDgAFAAhgBMAC4AI4AZYA7AB-AEYAI4AVeAtAC0gG8ASCAmIBNgCmwFsALkAXmAw8BkQDOQGeAM-AbkA_ACF4oAaANoAcwA8ACCgHVAR6AkUBrwDbwHEgPsAgeBBsZAaAAoAEMAJgAjgBlgDsgH2AfgBGACOAFXAK2AbwBJwCYgE2ALRAWwAvMBh4DIgGcgM8AZ8A-IB-AELxgAwAbQA5gB4AFiAOqAj0BIoC8gG3gOJAfYBBsAA.f_gACHgAAAAA"
          }
        ],
        "optOut": [
          {
            "name": "eupubconsent-v2",
            "value": "CPg0HVBPg0HVBAcABBENCFCgAAAAAAAAACiQAAAAAAEBoEIAVgAuACGAGQAMsAbIA7AB-AEAAIKARgAp4BV4C0ALSAawA3gB1QD5AIdARUAkQBNgCdgFIgLkAYSAw8BjADJwGcgM8AZ8A_AMAKAHMAdQBIQCRQGRgN0AcSA7MB7oEPhAAsAEgA5gDeAJCASKA3QBxIDswHugPsAh8IgNABWAEMAMgAZYA2QB2AD8AIAARgAp4BVwDWAHVAPkAh0BIgCbAE7AKRAXIAwkBh4DJwGcgM-AfgKgOAAUACGAEwALgAjgBlgDsAH4ARgAjgBV4C0ALSAbwBIICYgE2AKbAWwAuQBeYDDwGRAM5AZ4Az4BuQD8AIXigBoA2gBzADwAIKAdUBHoCRQGvANvAcSA-wCB4EGxkBoACgAQwAmACOAGWAOyAfYB-AEYAI4AVcArYBvAEnAJiATYAtEBbAC8wGHgMiAZyAzwBnwD4gH4AQvGADABtADmAHgAWIA6oCPQEigLyAbeA4kB9gEGwAAA.YAAAAAAAAAAA"
          }
        ]
      },
      "id": "dbbf625a-5a3f-4040-96c3-4633cc2d3e24"
    },
    {
      "click": {
        "optIn": "button.primary",
        "presence": "div.con-wizard"
      },
      "domain": "yahoo.com",
      "cookies": {
        "optIn": [
          {
            "name": "EuConsent",
            "value": "CPgyVIAPgyVIAAOACBROCkCoAP_AAH_AACiQJBNd_H__bX9n-f7_6ft0eY1f9_r37uQzDhfNk-8F3L_W_LwX_2E7NF36tq4KmR4ku1LBIUNtHMnUDUmxaokVrzHsak2cpzNKJ_BkknsZe2dYGF9vm5tj-QKZ7_5_d3f52T_9_9v-39z33913v3d93-_13LjdV5_9H_v9fR_bc_Kft_5-_8v8_____3_e______8EggCTDVuIAuxLHAm0DCKBECMKwkKoFABBQDC0QGADg4KdlYBPrCBAAgFAEYEQIcAUYEAgAAAgCQiACQIsEAAAIgEAAIAEQiEABAwCCgAsDAIAAQDQMUQoABAkIMiAiKUwICIEggJbKhBKC6Q0wgDrLACgkRsVAAiAAAUgACAsHAMESAlYsECTFG-QAjBCgFEqFaAGGgAwABBIIRABgACCQQqADAAEEgg",
            "isSecure": true
          }
        ]
      },
      "id": "2f9123b1-7d6b-460f-8da8-988f82238ec7"
    },
    {
      "click": {
        "optIn": "button.cmd-button-accept-all",
        "optOut": "button.cmd-button-reject-all",
        "presence": "div.cookies-modal"
      },
      "domain": "xhamster.com",
      "cookies": {
        "optIn": [
          {
            "name": "cookie_accept",
            "value": "%7B%22e%22%3A1%2C%22n%22%3A1%2C%22tp%22%3A1%7D"
          }
        ],
        "optOut": [
          {
            "name": "cookie_accept",
            "value": "%7B%22e%22%3A1%2C%22n%22%3A0%2C%22tp%22%3A0%7D"
          }
        ]
      },
      "id": "02e04a3d-0848-4b10-a41d-80e31c4062a7"
    },
    {
      "click": {
        "optIn": ".btn--primary",
        "presence": "div#cookie-consent"
      },
      "domain": "opera.com",
      "cookies": {
        "optIn": [
          {
            "name": "cookie_consent_essential",
            "value": "true"
          },
          {
            "name": "cookie_consent_marketing",
            "value": "true"
          }
        ]
      },
      "id": "09884f7b-ef06-45dd-9bda-960b5c6b7232"
    },
    {
      "click": {
        "optIn": "#cmpbntyestxt",
        "optOut": "#cmpbntnotxt",
        "presence": "div.cmpboxbtns"
      },
      "domain": "sourceforge.net",
      "cookies": {
        "optIn": [
          {
            "name": "__cmpconsentx11319",
            "value": "CPgx6wgPgx6wgAfUnBENCkCsAP_AAH_AACiQGgwDwAGgAVABAADQAJgAXwAwgB4AEEAJAAUYBCAFoALzAaCBoMA8ABoAFQAQAA0ACYAF8AMIAeABBACQAFGAQgBaAC8wGggAAA",
            "isSecure": true
          }
        ],
        "optOut": [
          {
            "name": "__cmpconsentx11319",
            "value": "CPgx6wgPgx6wgAfUnBENCkCgAAAAAAAAACiQAAAAAAAA",
            "isSecure": true
          }
        ]
      },
      "id": "786f7ae5-548a-43d4-97a2-7b8efb5ed7a7"
    },
    {
      "click": {
        "optIn": "button#onetrust-accept-btn-handler",
        "presence": "div#onetrust-consent-sdk"
      },
      "domain": "digicert.com",
      "cookies": {},
      "id": "0da6a0df-beac-4499-b3ac-023fc68ca695"
    },
    {
      "click": {
        "optIn": "button#onetrust-accept-btn-handler",
        "optOut": "button#onetrust-reject-all-handler",
        "presence": "div#onetrust-consent-sdk"
      },
      "domain": "webex.com",
      "cookies": {},
      "id": "5e777243-0819-48a6-90b4-66a1353e2514"
    },
    {
      "click": {
        "optIn": "div#gdpr-single-choice-overlay",
        "presence": "button.wt-btn--filled"
      },
      "domain": "etsy.com",
      "cookies": {
        "optIn": [
          {
            "name": "p",
            "value": "eyJnZHByX3RwIjoxLCJnZHByX3AiOjF9"
          }
        ]
      },
      "id": "e5706488-f2e9-47bd-a178-4d569ca26ce8"
    },
    {
      "click": {
        "optIn": "button#onetrust-accept-btn-handler",
        "optOut": "button#onetrust-reject-all-handler",
        "presence": "div#onetrust-consent-sdk"
      },
      "domain": "indeed.com",
      "cookies": {},
      "id": "a4d94551-fc83-4477-b542-a13950b97468"
    },
    {
      "click": {
        "optIn": "button#L2AGLb",
        "optOut": "button#W0wltc",
        "presence": "div.spoKVd"
      },
      "domain": "google.co.in",
      "cookies": {
        "optIn": [
          {
            "name": "SOCS",
            "value": "CAISHAgBEhJnd3NfMjAyMjEwMTAtMF9SQzIaAnJvIAEaBgiA2beaBg"
          },
          {
            "name": "CONSENT",
            "value": "PENDING"
          }
        ],
        "optOut": [
          {
            "name": "SOCS",
            "value": "CAESHAgBEhJnd3NfMjAyMjA5MjEtMF9SQzQaAnJvIAEaBgiA49iZBg"
          },
          {
            "name": "CONSENT",
            "value": "CAISHAgBEhJnd3NfMjAyMjEwMTAtMF9SQzIaAnJvIAEaBgiA2beaBg"
          }
        ]
      },
      "id": "9c252bbd-0ddc-4677-bab1-3946161dc819"
    },
    {
      "click": {
        "optIn": "button#onetrust-accept-btn-handler",
        "presence": "div#onetrust-consent-sdk"
      },
      "domain": "weebly.com",
      "cookies": {
        "optIn": [
          {
            "name": "cookie-consent",
            "value": "{\"allowStrictlyNecessaryCookies\":true,\"allowFunctionalityCookies\":true,\"allowPerformanceCookies\":true,\"allowTargetingCookies\":true}"
          }
        ]
      },
      "id": "eed2da2f-466d-4f5e-8138-73103b881cdc"
    },
    {
      "click": {
        "optIn": "button#CybotCookiebotDialogBodyLevelButtonLevelOptinAllowAll",
        "optOut": "button#CybotCookiebotDialogBodyButtonDecline",
        "presence": "div#CybotCookiebotDialog"
      },
      "domain": "issuu.com",
      "cookies": {},
      "id": "019c0709-e9ef-4b0d-94bf-958d251a51b5"
    },
    {
      "click": {
        "optIn": "button#onetrust-accept-btn-handler",
        "presence": "div#onetrust-consent-sdk"
      },
      "domain": "salesforce.com",
      "cookies": {},
      "id": "f092364a-505d-11ed-bdc3-0242ac120002"
    },
    {
      "click": {
        "optIn": "button#onetrust-accept-btn-handler",
        "optOut": "button#onetrust-reject-all-handler",
        "presence": "div#onetrust-consent-sdk"
      },
      "domain": "discord.com",
      "cookies": {},
      "id": "93bb70d2-5065-11ed-bdc3-0242ac120002"
    },
    {
      "click": {
        "optIn": "button#onetrust-accept-btn-handler",
        "presence": "div#onetrust-consent-sdk"
      },
      "domain": "reuters.com",
      "cookies": {},
      "id": "343ee5ca-506b-11ed-bdc3-0242ac120002"
    },
    {
      "click": {
        "optIn": "button#onetrust-accept-btn-handler",
        "presence": "div#onetrust-consent-sdk"
      },
      "domain": "booking.com",
      "cookies": {},
      "id": "ae6bb1b6-506b-11ed-bdc3-0242ac120002"
    },
    {
      "click": {
        "optIn": "button.agree-btn",
        "presence": "div.message-column main-container"
      },
      "domain": "wsj.com",
      "cookies": {},
      "id": "edc06db8-5073-11ed-bdc3-0242ac120002"
    },
    {
      "click": {
        "optIn": "button.sp_choice_type_11",
        "presence": "div.message-container"
      },
      "domain": "bloomberg.com",
      "cookies": {
        "optIn": [
          {
            "name": "euconsent-v2",
            "value": "CPhJZsAPhJZsAAGABCENClCgAP_AAGPAACJwH9oB9CpGCTFDKGh4AIsAEAQXwBAEAOAAAAABAAAAAAgQAIwCAEASAACAAAACAAAAIAIAAAAAEAAAAEAAQAAAAAFAAAAEAAAAAAAAAAAAAAAAAAAAAIEAAAAAAUAAAFAAgEAAABIAQAQAAAAAAAAAAAAAAAAAAAAAAAAAAAAAAAAAgYtAQAAcACEAHIAPwBHAEDgIOAhABEQCLAF1AMCAa8A6gCygF5gMWAMGQBQAmACOAI4ApsBeYiAIAA4ArICmwFyBIC4ACwAKgAZAA4ACAAGQANIAiACKAEwAJ4AfgBCACOAFKAO8AewBHACUgFZAOIApsBcgDJA0AQABwBWQFNgLkFQBgAmACOAI4ApsBcgC8x0BsABYAFQAMgAcABAAC4AGQANIAiACKAEwAJ4AYgA_ACYAFGAKUAZQA7wB7AEcAJSAVkA4gB1AFNgLkAZIOAAgAXIQDgAFgAZABcAEwAMQAjgBSgDvAI4ASkArIB1AFNgLkJQDQAFgAZAA4AEQAJgAYgBHACjAFKAO8AjgBWQDqEgAIAFykBYABYAFQAMgAcABAADIAGkARABFACYAE8AMQAfgBRgClAGUAO8AjgBKQCsgKbAXIAyQoABAAuAA.YAAAAAAAAAAA",
            "isSecure": true
          }
        ],
        "optOut": [
          {
            "name": "euconsent-v2",
            "value": "CPhJZsAPhJZsAAGABCENClCgAAAAAAAAACJwAAAAAAAA.YAAAAAAAAAAA",
            "isSecure": true
          }
        ]
      },
      "id": "672228d2-5078-11ed-bdc3-0242ac120002"
    },
    {
      "click": {
        "optIn": "button.RMlTST",
        "presence": "div.aspXfg"
      },
      "domain": "wix.com",
      "cookies": {},
      "id": "aa245048-507c-11ed-bdc3-0242ac120002"
    },
    {
      "click": {
        "optIn": "button.sp_choice_type_11",
        "presence": "div#notice"
      },
      "domain": "businessinsider.com",
      "cookies": {
        "optIn": [
          {
            "name": "euconsent-v2",
            "value": "CPhZ4YAPhZ4YAAGABCENCmCsAP_AAELAACJwHmQHAAFAAVAAyABwAEAAKgAWgA0AB6AEWAJgAmgBVAC2AG4AQgAjgBRgCtAFyAXUAwIBtAD9ALZAXmAxkBkgDzAGBgDAAVABoAI4AXIBdQDAgDjIAYATABHALzCQCwAMgAcABAAEUAJgAVQBCACOANoAvMBkgqAGAEwARwC8x0AoADIAHAAQABFACYAFUAUYBtAF5gMkIQBQAMgBMACqAI4A2hKAOABkADgATAAqgCOAFGAvMpAKAAyABwAEAARQAmABVAFGAbQBeYDJAAAA.YAAAAAAAAAAA"
          }
        ],
        "optOut": [
          {
            "name": "euconsent-v2",
            "value": "CPhZ4YAPhZ4YAAGABBENCmCgAAAAAELAACJwAAAGBgDAAVABoAI4AXIBdQDAgAAA.YAAAAAAAAAAA"
          }
        ]
      },
      "id": "a72a4c14-1f68-40b0-aaf5-ee76b7acf4d6"
    },
    {
      "click": {
        "optIn": "button#onetrust-accept-btn-handler",
        "presence": "div#onetrust-button-group"
      },
      "domain": "20min.ch",
      "cookies": {},
      "id": "24c6ffc2-7a11-4401-a1fe-2cec15a1a76d"
    },
    {
      "click": {
        "optIn": "button#L2AGLb",
        "optOut": "button#W0wltc",
        "presence": "div.spoKVd"
      },
      "domain": "google.at",
      "cookies": {
        "optIn": [
          {
            "name": "CONSENT",
            "value": "PENDING"
          }
        ],
        "optOut": [
          {
            "name": "SOCS",
            "value": "CAESHAgBEhJnd3NfMjAyMjA5MjktMF9SQzEaAnJvIAEaBgiAkvOZBg"
          }
        ]
      },
      "id": "4a37ab17-dbd7-45cf-83d8-42b84af9a0df"
    },
    {
      "click": {
        "optIn": "button#L2AGLb",
        "optOut": "button#W0wltc",
        "presence": "div.spoKVd"
      },
      "domain": "google.be",
      "cookies": {
        "optIn": [
          {
            "name": "CONSENT",
            "value": "PENDING"
          }
        ],
        "optOut": [
          {
            "name": "SOCS",
            "value": "CAESHAgBEhJnd3NfMjAyMjA5MjktMF9SQzEaAnJvIAEaBgiAkvOZBg"
          }
        ]
      },
      "id": "155e345a-0391-4148-98ba-9a409bc8063f"
    },
    {
      "click": {
        "optIn": "button#didomi-notice-agree-button",
        "presence": "div#buttons"
      },
      "domain": "orf.at",
      "cookies": {
        "optIn": [
          {
            "name": "euconsent-v2",
            "value": "CPgX9oAPgX9oAAHABBENCjCgAPLAAAAAAACYHVQIQADAAVABBACcAKAAWAAyABpAEQARoAmgCeAH4AQIAhABUADVAIQARMAiwBOAC6gGBAMUAfYA_QCCQEagJaAV-AvMBjIDGwGWAOagdSB1QAAACQkAGAAIJBDoAMAAQSCJQAYAAgkEGgAwABBIIUABgACCQRSADAAEEgiAAGAAIJBCIAMAAQSCGAAYAAgkEAAA.flgAAAAAAAAA"
          }
        ],
        "optOut": [
          {
            "name": "euconsent-v2",
            "value": "CPgX9oAPgX9oAAHABBENCjCgAAAAAAAAAACYAAAAAAEhIAMAAQSCHQAYAAgkESgAwABBIINABgACCQQoADAAEEgikAGAAIJBEAAMAAQSCEQAYAAgkEMAAwABBIIA.YAAAAAAAAAAA"
          }
        ]
      },
      "id": "55ce89fe-e609-46b4-85db-be8a040bf41d"
    },
    {
      "click": {
        "optIn": "button#didomi-notice-agree-button",
        "presence": "div#buttons"
      },
      "domain": "abv.bg",
      "cookies": {
        "optIn": [
          {
            "name": "euconsent-v2",
            "value": "CPgX9oAPgX9oAAHABBENCjCsAP_AAE7AAAIwGMwFgAFAANAAgABUADoAIAAVAAyABoAEUALYAYQBCAFIATSAo8BUgC4QFygLpAXmAxkC84A4AFQAQAAyABoAEUAQgC8wAg0AGAAIJBCIAMAAQSCA.f_gACdgAAAAA"
          }
        ],
        "optOut": [
          {
            "name": "euconsent-v2",
            "value": "CPgX9oAPgX9oAAHABBENCjCgAAAAAAAAAAIwAAAAAABBoAMAAQSCEQAYAAgkEAAA.YAAAAAAAAAAA"
          }
        ]
      },
      "id": "8d7e2b6c-b276-410a-838f-3685b4fe7cac"
    },
    {
      "click": {
        "optIn": "button.submitAll",
        "presence": "div.submitButton"
      },
      "domain": "dr.dk",
      "cookies": {
        "optIn": [
          {
            "name": "CookieConsent",
            "value": "{stamp:%272Wv5SQ2S2WiaKDYUJJCdPOTrSbeFVWR11Lxbrkc5K1CcpesiF9QZ+A==%27%2Cnecessary:true%2Cpreferences:true%2Cstatistics:true%2Cmarketing:true%2Cver:5%2Cutc:1667308125393%2Cregion:%27ro%27}"
          }
        ],
        "optOut": [
          {
            "name": "CookieConsent",
            "value": "{stamp:%27D1AamT1V80siZwfIuWr5SREHguKw3sySW3+Q+Nb2mPwfRB9so2m1Sg==%27%2Cnecessary:true%2Cpreferences:false%2Cstatistics:false%2Cmarketing:false%2Cver:5%2Cutc:1664957253372%2Cregion:%27ro%27}"
          }
        ]
      },
      "id": "9def1218-9201-4b49-bf69-ea203aeab2b3"
    },
    {
      "click": {
        "optIn": "button#L2AGLb",
        "optOut": "button#W0wltc",
        "presence": "div.spoKVd"
      },
      "domain": "google.it",
      "cookies": {
        "optIn": [
          {
            "name": "CONSENT",
            "value": "PENDING"
          }
        ],
        "optOut": [
          {
            "name": "SOCS",
            "value": "CAESHAgBEhJnd3NfMjAyMjA5MjktMF9SQzEaAnJvIAEaBgiAkvOZBg"
          }
        ]
      },
      "id": "1e68867f-8537-480f-a729-edc8d76ccc6c"
    },
    {
      "click": {
        "optIn": "button#L2AGLb",
        "optOut": "button#W0wltc",
        "presence": "div.spoKVd"
      },
      "domain": "google.pt",
      "cookies": {
        "optIn": [
          {
            "name": "CONSENT",
            "value": "PENDING"
          }
        ],
        "optOut": [
          {
            "name": "SOCS",
            "value": "CAESHAgBEhJnd3NfMjAyMjA5MjktMF9SQzEaAnJvIAEaBgiAkvOZBg"
          }
        ]
      },
      "id": "45e8f894-cc1f-471a-8147-366f6f5b23a1"
    },
    {
      "click": {
        "optIn": "button.sp_choice_type_11",
        "presence": "div#notice"
      },
      "domain": "aktuality.sk",
      "cookies": {
        "optOut": [
          {
            "name": "euconsent-v2",
            "value": "CPgX9oAPgX9oAAGABBENCjCgAAAAAAAAACJwAAAAAAAA.YAAAAAAAAAAA"
          }
        ]
      },
      "id": "ec724813-ccf8-4113-bd94-254f6a51d7d1"
    },
    {
      "click": {
        "optIn": "button#L2AGLb",
        "optOut": "button#W0wltc",
        "presence": "div.spoKVd"
      },
      "domain": "google.bg",
      "cookies": {
        "optIn": [
          {
            "name": "CONSENT",
            "value": "PENDING"
          }
        ],
        "optOut": [
          {
            "name": "SOCS",
            "value": "CAESHAgBEhJnd3NfMjAyMjA5MjktMF9SQzEaAnJvIAEaBgiAkvOZBg"
          }
        ]
      },
      "id": "1e3cbc4f-896a-42ad-93c9-d357697290d8"
    },
    {
      "click": {
        "optIn": "button#didomi-notice-agree-button",
        "presence": "div#buttons"
      },
      "domain": "jutarnji.hr",
      "cookies": {},
      "id": "fd22bda9-14dc-4777-92f0-971d474d4ee7"
    },
    {
      "click": {
        "optIn": "button#almacmp-modalConfirmBtn",
        "presence": "div.almacmp-controls"
      },
      "domain": "iltalehti.fi",
      "cookies": {},
      "id": "23fcab4a-3b43-4d73-bb9e-57d86121141b"
    },
    {
      "click": {
        "optIn": "button#didomi-notice-agree-button",
        "presence": "div#buttons"
      },
      "domain": "orange.fr",
      "cookies": {},
      "id": "dd60c9fc-2800-45b1-abd7-2ec401ff68b5"
    },
    {
      "click": {
        "optIn": "button#L2AGLb",
        "optOut": "button#W0wltc",
        "presence": "div.spoKVd"
      },
      "domain": "google.gr",
      "cookies": {
        "optIn": [
          {
            "name": "CONSENT",
            "value": "PENDING"
          }
        ],
        "optOut": [
          {
            "name": "SOCS",
            "value": "CAESHAgBEhJnd3NfMjAyMjA5MjktMF9SQzEaAnJvIAEaBgiAkvOZBg"
          }
        ]
      },
      "id": "029b3695-6b57-423e-8d7d-78abfba94f51"
    },
    {
      "click": {
        "optIn": "button#L2AGLb",
        "optOut": "button#W0wltc",
        "presence": "div.spoKVd"
      },
      "domain": "google.hu",
      "cookies": {
        "optIn": [
          {
            "name": "CONSENT",
            "value": "PENDING"
          }
        ],
        "optOut": [
          {
            "name": "SOCS",
            "value": "CAESHAgBEhJnd3NfMjAyMjA5MjktMF9SQzEaAnJvIAEaBgiAkvOZBg"
          }
        ]
      },
      "id": "682598ca-1742-4689-ad95-7c70f2a01511"
    },
    {
      "click": {
        "optIn": "button#L2AGLb",
        "optOut": "button#W0wltc",
        "presence": "div.spoKVd"
      },
      "domain": "google.nl",
      "cookies": {
        "optIn": [
          {
            "name": "CONSENT",
            "value": "PENDING"
          }
        ],
        "optOut": [
          {
            "name": "SOCS",
            "value": "CAESHAgBEhJnd3NfMjAyMjA5MjktMF9SQzEaAnJvIAEaBgiAkvOZBg"
          }
        ]
      },
      "id": "e3af03b3-8990-45ef-abd5-f6da31bd31fe"
    },
    {
      "click": {
        "optIn": "button.cmp-intro_acceptAll",
        "presence": "div.cmp-intro_options"
      },
      "domain": "onet.pl",
      "cookies": {},
      "id": "be15b898-a203-45cb-8200-b9b36d2af17b"
    },
    {
      "click": {
        "optIn": "button#L2AGLb",
        "optOut": "button#W0wltc",
        "presence": "div.spoKVd"
      },
      "domain": "google.ro",
      "cookies": {
        "optIn": [
          {
            "name": "CONSENT",
            "value": "PENDING"
          }
        ],
        "optOut": [
          {
            "name": "SOCS",
            "value": "CAESHAgBEhJnd3NfMjAyMjA5MjktMF9SQzEaAnJvIAEaBgiAkvOZBg"
          }
        ]
      },
      "id": "8115b20d-9faa-41e2-8775-9f1630e29182"
    },
    {
      "click": {
        "optIn": "button#L2AGLb",
        "optOut": "button#W0wltc",
        "presence": "div.spoKVd"
      },
      "domain": "google.rs",
      "cookies": {
        "optIn": [
          {
            "name": "CONSENT",
            "value": "PENDING"
          }
        ],
        "optOut": [
          {
            "name": "SOCS",
            "value": "CAESHAgBEhJnd3NfMjAyMjA5MjktMF9SQzEaAnJvIAEaBgiAkvOZBg"
          }
        ]
      },
      "id": "ab57e25b-97a6-435b-a032-1f05da420d78"
    },
    {
      "click": {
        "optIn": "button.fc-cta-consent",
        "presence": "div.fc-footer-buttons-container"
      },
      "domain": "sme.sk",
      "cookies": {
        "optOut": [
          {
            "name": "FCCDCF",
            "value": "%5Bnull%2Cnull%2Cnull%2C%5B%22CPgX9oAPgX9oAEsABBSKCjCgAAAAAH_AACRQAAARWQD2N2K2urOkfnWUWaoQRKuj6UMlUBEAAGKBIgAKV0tWVgH-oAwAJlkCVARIgxBZIQCQgAQABGICoMikAKIWAEAAAEhBAIQQ2DJILYCAECAIJgGBwKCEAARwNzQSEShkhqR1RVpOxlkt4Zr7CZCp8GdpOG09xbTFlYa8AJzwYEYZoSUrlyY6d-vomMgAAA.YAAACFgAAAA%22%2C%221~%22%2C%22A929B7B4-F769-45F3-AF99-5736CCFF0CA8%22%5D%2Cnull%2Cnull%2C%5B%5D%5D"
          }
        ]
      },
      "id": "a7a48015-5705-4f45-8abd-f7a1e38df511"
    },
    {
      "click": {
        "optIn": "button#L2AGLb",
        "optOut": "button#W0wltc",
        "presence": "div.spoKVd"
      },
      "domain": "google.es",
      "cookies": {
        "optIn": [
          {
            "name": "CONSENT",
            "value": "PENDING"
          }
        ],
        "optOut": [
          {
            "name": "SOCS",
            "value": "CAESHAgBEhJnd3NfMjAyMjA5MjktMF9SQzEaAnJvIAEaBgiAkvOZBg"
          }
        ]
      },
      "id": "34bf1a0c-66c2-4f35-8efa-2c31d23c2615"
    },
    {
      "click": {
        "optIn": "button#didomi-notice-agree-button",
        "presence": "div#buttons"
      },
      "domain": "expressen.se",
      "cookies": {
        "optOut": [
          {
            "name": "euconsent-v2",
            "value": "CPgX9oAPgX9oAAHABBENCjCgAAAAAAAAACQgAAAAAAAA.YAAAAAAAAAAA"
          }
        ]
      },
      "id": "64efa4eb-bedd-4fdf-8f6b-0e7376b6282d"
    },
    {
      "click": {
        "optIn": "button#L2AGLb",
        "optOut": "button#W0wltc",
        "presence": "div.spoKVd"
      },
      "domain": "google.ca",
      "cookies": {
        "optIn": [
          {
            "name": "CONSENT",
            "value": "PENDING"
          }
        ],
        "optOut": [
          {
            "name": "SOCS",
            "value": "CAESHAgBEhJnd3NfMjAyMjA5MjktMF9SQzEaAnJvIAEaBgiAkvOZBg"
          }
        ]
      },
      "id": "8e4491e1-70dd-4f0f-9968-c4bf7d6129b2"
    },
    {
      "click": {
        "optIn": "button#didomi-notice-agree-button",
        "presence": "div#buttons"
      },
      "domain": "nieuwsblad.be",
      "cookies": {
        "optIn": [
          {
            "name": "cto_bundle",
            "value": "_zkE719xMmNsWlRTd2l2SGFBZVpzYkRialZYZXY1Z3hjWDhxc1RBNDR6MkhjMDBEdHVLVjdISkdrUHJUc0tmMGRUVW5pZmxLNG0xcGdoVWdYNkVzbjc2NDBTSkJsVlhKU09hdktyaGtNeHd6S0JKT2F5aWgxY09ERVBFRmxaTlE1Rk9ENE54dlQ1c3dzb0xUNUJOV3pZUU04cEElM0QlM0Q"
          }
        ],
        "optOut": [
          {
            "name": "euconsent-v2",
            "value": "CPgX9oAPgX9oAAHABBENCjCgAAAAAAAAAAAAAAAAAAAhoAMAAQSC.YAAAAAAAAAAA"
          }
        ]
      },
      "id": "a722d5b5-5229-4658-ab48-b0adfdf49253"
    },
    {
      "click": {
        "optIn": "button#didomi-notice-agree-button",
        "presence": "div#buttons"
      },
      "domain": "vecernji.hr",
      "cookies": {},
      "id": "fd53040e-b5e6-4e12-8083-859f9d75bb38"
    },
    {
      "click": {
        "optIn": "button#didomi-notice-agree-button",
        "presence": "div#buttons"
      },
      "domain": "idnes.cz",
      "cookies": {
        "optOut": [
          {
            "name": "euconsent-v2",
            "value": "CPgX9oAPgX9oAAHABBENCjCgAAAAAAAAAATIAAAAAACBoAMAAQSCEQAYAAgkEKgAwABBIIZABgACCQQA.YAAAAAAAAAAA"
          }
        ]
      },
      "id": "69447c31-c678-40a9-a779-b618f71461ca"
    },
    {
      "click": {
        "optIn": "button#onetrust-accept-btn-handler",
        "optOut": "button#onetrust-reject-all-handler",
        "presence": "div#onetrust-button-group"
      },
      "domain": "tv2.dk",
      "cookies": {
        "optOut": []
      },
      "id": "bcaf0219-c4b8-4c03-aeed-6b7111e3bbf1"
    },
    {
      "click": {
        "optIn": "button#accept-all",
        "optOut": "button#accept-essential",
        "presence": "div.actions"
      },
      "domain": "skroutz.gr",
      "cookies": {
        "optOut": [
          {
            "name": "policy_level",
            "value": "%7B%22essential%22%3A%22true%22%2C%22performance%22%3A%22false%22%2C%22preference%22%3A%22false%22%2C%22targeting%22%3A%22false%22%7D"
          }
        ]
      },
      "id": "fc149ac6-5a51-49fb-bb14-2c2dce8f6628"
    },
    {
      "click": {
        "optIn": "button.css-1wjnr64",
        "presence": "div.qc-cmp2-summary-buttons"
      },
      "domain": "idokep.hu",
      "cookies": {
        "optOut": [
          {
            "name": "euconsent-v2",
            "value": "CPgX9oAPgX9oAAKAoBHUCjCgAAAAAH_AAA6gAAASCAIMBEAgAAMEAEIAAAIAAAQACQAgAAABAABQAIAOCgACFgEQAIAACAQAQgAAhBAQAQAAAAQAJAAABACwQCAAAAQAAgABAAAAMBAADACQMAAAAAJARRCAAECAAiAAApCAAKACCAUIAAAAKJDACAOsoAADBAhUACJJAQCAABCwMAwQICViQAFAACgACEEKAUSgQoBISCuAAgABcAFAAVAAyAByADwAQAAwgBkAGoAPIAhgCKAEwAJ4AVQA3gBzAD0AH4AQkAhgCJAEcAJYATQApQBbgDDAGQAMsAbIA74B7AHxAPsA_YB_gIGARSAi4CMQEaARwAlIBQQCngFXALmAaIA1gBtADcAHEAPQAfIBDoCIQEiAJlATsAocBSICmgFigLQAWwAuQBd4C8wGDAMNgZGBkgDJwGXAM5AZ8A0iBrAGsgNvAbqA4IBxEDkwOUAcuA8cB7QEIYIXAheBDkCHoEPwIhgRSAj6BH8lA-AAQAAsACgAGQAOAAfgBgAGIAPAAiABMACqAFwAMQAZoBDAESAI4AUYApQBbgDCAGUANkAd8A-wD8AI4AU8Aq8BaAFpgLmAuoBigDcAHUAPkAfYBDoCJgEVAIvASIAsUBZQC2AF2gLzAZGAycBlgDOYGeAZ8A0gBrADbwHAAPaAgCBA8CEIELwIagQ9AiyBH8dBrAAXABQAFQAMgAcgA-AEAALoAYABqADwAH0AQwBFACYAE8AKsAXABdADEAGYAN4AcwA9AB-gEMARMAlgCYAE0AKMAUoAsQBbwDCAMOAZABlADRAGyAO8Ae0A-wD9AH-AQMAikBFgEYgI4AjoBKQCggFPAKuAWKAtAC0wFzAXWAvIC9AGKANoAbgA4gBzgDqAHoAPsAh0BEICKgEXgJEASoAmQBOwChwFNAKsAWKAsoBbAC4AFyALtAXeAvMBfQDBgGGgMegZGBkgDJwGVQMsAy4BmYDOQGfANEgaQBpIDVQGsANvAbqA4gBxcDkwOUAcuA8cB7QD6wIAgQaAhfBDkEOgIegRSAjsBH0CP5CCEAAsACgAGQAXAAxABqAEMAJgAUwAqgBcADEAGYAN4AegBHAClAFiAMIAZQA7wB9gD_AIoARwAlIBQQCngFXgLQAtIBcwDFAG0AOcAdQA9ACIQEiAJOASoApoBVgCxQFlALRAWwAuABcgC7QGRgMnAZzAzwDPgGiANJAaqA4ABxADlAHjgQoAheBDoCHoEfQI_lIKQAC4AKAAqABkADkAHwAggBgAGoAPIAhgCKAEwAJ4AUgAqgBiADMAHMAP0AhgCJAFGAKUAWIAtwBhQDIAMoAaIA2QB3wD7AP0AiwBGICOAI6ASkAoIBVwCtgFzALyAYoA2gBuAD0AH2AQ6AiYBF4CRAEnAJ2AUOAqwBYoC0AFsALgAXIAu0BeYC-gGGwMjAyQBk8DLAMuAZzAzwDPoGkAaTA1gDWQG3gN1AcFA5MDlAHLgPFAeOA9oCEIELwIZgQ6Ah6BEACKQEdgI_ioCYAFAAhgBMAC4AI4AZYBHACrwFoAWkBbAC5AF5gMjAZzAzwDPgG5AOUAheBH8ZASACGAEwARwAywCOAFXAK2Ak4BaIC2AFyALzAZGAzmBngGfAOUAheBH8NAcAC4AIYAZAAywBswD7APwAgABBQCMAFPAKvAWgBaQDWAHVAPkAh0BEwCKgEiAJ2AUiAuQBkYDJwGcwM8Az4BygEfxEBcAQwAyABlgDZgH2AfgBAACMAFPAKuAawA6oB8gEOgJEATsApEBcgDIwGTgM5AZ8A5QCP4.YAAAAAAAAAAA"
          }
        ]
      },
      "id": "1dc10ed2-800f-484c-9df1-6f99d8cd2584"
    },
    {
      "click": {
        "optIn": "button.js-accept",
        "presence": "div.cookie-banner-buttons"
      },
      "domain": "emag.ro",
      "cookies": {},
      "id": "dbbccc0a-13ba-4cd8-9cf0-32420401be55"
    },
    {
      "click": {
        "optIn": "button.CookieConsent_button__FJrIc",
        "presence": "div.CookieConsent_holder__ZsT3G"
      },
      "domain": "kupujemprodajem.com",
      "cookies": {
        "optIn": [
          {
            "name": "FCNEC",
            "value": "%5B%5B%22AKsRol-hQ0GC8scayCxS70oIbLW375lxZBB419tjfwu1fOoWf-QLr5NOEOgKKLPu5Em82ydIwG4STH2DOpPVM65ZS_y2CCQlVsaUDCu-KZl2LrrYKqTftQDxBBuO-EmausJD4fO6ZHNWJEHTyKM8wJgrIadkxR4m9g%3D%3D%22%5D%2Cnull%2C%5B%5D%5D"
          }
        ],
        "optOut": [
          {
            "name": "FCCDCF",
            "value": "%5Bnull%2Cnull%2Cnull%2C%5B%22CPgX9oAPgX9oAEsABCENCjCgAAAAAAAAABpYAAAOhQD2F2K2kKEkfjSUWYAQBCujIEIBUAAAAECBIAAAAUgQAgFIIAgAAlACAAAAABAQAQCAgAQABAAAoACgACAAAAAAAAAAAAQQAABAAIAAAAAAAAEAQAAAAAQAAAAAAABEhCAAQQAEAAAAAAAAAAAAAAAAAAABAAA.YAAAAAAAAAA%22%2C%221~%22%2C%22D2A36A86-FAFB-4BB0-951A-2BA964C5C018%22%5D%2Cnull%2Cnull%2C%5B%5D%5D"
          }
        ]
      },
      "id": "944c0cf0-271b-41f8-b0ca-3fa67db7af29"
    },
    {
      "click": {
        "optIn": "button#L2AGLb",
        "optOut": "button#W0wltc",
        "presence": "div.spoKVd"
      },
      "domain": "google.sk",
      "cookies": {
        "optIn": [
          {
            "name": "CONSENT",
            "value": "PENDING"
          }
        ],
        "optOut": [
          {
            "name": "SOCS",
            "value": "CAESHAgBEhJnd3NfMjAyMjA5MjktMF9SQzEaAnJvIAEaBgiAkvOZBg"
          }
        ]
      },
      "id": "f56f7d8e-028e-4407-b593-c8b2e27fe925"
    },
    {
      "click": {
        "optIn": "button#didomi-notice-agree-button",
        "presence": "div#buttons"
      },
      "domain": "marca.com",
      "cookies": {},
      "id": "af4c5b38-d210-472b-9a07-21cbe53c85ab"
    },
    {
      "click": {
        "optIn": "button#L2AGLb",
        "optOut": "button#W0wltc",
        "presence": "div.spoKVd"
      },
      "domain": "google.se",
      "cookies": {
        "optIn": [
          {
            "name": "CONSENT",
            "value": "PENDING"
          }
        ],
        "optOut": [
          {
            "name": "SOCS",
            "value": "CAESHAgBEhJnd3NfMjAyMjA5MjktMF9SQzEaAnJvIAEaBgiAkvOZBg"
          }
        ]
      },
      "id": "7877bb19-0224-4742-add6-e0d432c04f41"
    },
    {
      "click": {
        "optIn": "button#L2AGLb",
        "optOut": "button#W0wltc",
        "presence": "div.spoKVd"
      },
      "domain": "google.ch",
      "cookies": {
        "optIn": [
          {
            "name": "CONSENT",
            "value": "PENDING"
          }
        ],
        "optOut": [
          {
            "name": "SOCS",
            "value": "CAESHAgBEhJnd3NfMjAyMjA5MjktMF9SQzEaAnJvIAEaBgiAkvOZBg"
          }
        ]
      },
      "id": "2ec85a22-122c-42bc-be9e-7e406a3fe527"
    },
    {
      "click": {
        "optIn": "button.sp_choice_type_11",
        "presence": "div#notice"
      },
      "domain": "bild.de",
      "cookies": {},
      "id": "ece4e912-63b8-4533-9302-9d55b62b40aa"
    },
    {
      "click": {
        "optIn": "button#didomi-notice-agree-button",
        "optOut": "button#didomi-notice-disagree-button",
        "presence": "div#buttons"
      },
      "domain": "krone.at",
      "cookies": {},
      "id": "83fdefbb-23f4-450f-a971-46651200e419"
    },
    {
      "click": {
        "optIn": "button#didomi-notice-agree-button",
        "presence": "div#buttons"
      },
      "domain": "24sata.hr",
      "cookies": {},
      "id": "7f747f1b-f00e-4179-a285-8a4916ef509a"
    },
    {
      "click": {
        "optIn": "button#L2AGLb",
        "optOut": "button#W0wltc",
        "presence": "div.spoKVd"
      },
      "domain": "google.dk",
      "cookies": {
        "optIn": [
          {
            "name": "CONSENT",
            "value": "PENDING"
          }
        ],
        "optOut": [
          {
            "name": "SOCS",
            "value": "CAESHAgBEhJnd3NfMjAyMjA5MjktMF9SQzEaAnJvIAEaBgiAkvOZBg"
          }
        ]
      },
      "id": "b0f69a37-2fad-47f4-bcd1-e08bbcd232e7"
    },
    {
      "click": {
        "optIn": "button#L2AGLb",
        "optOut": "button#W0wltc",
        "presence": "div.spoKVd"
      },
      "domain": "google.fi",
      "cookies": {
        "optIn": [
          {
            "name": "CONSENT",
            "value": "PENDING"
          }
        ],
        "optOut": [
          {
            "name": "SOCS",
            "value": "CAESHAgBEhJnd3NfMjAyMjEwMDMtMF9SQzEaAnJvIAEaBgiAtfiZBg"
          }
        ]
      },
      "id": "0c81f056-566c-4d00-9595-d68d4f3a87f1"
    },
    {
      "click": {
        "optIn": "button.fc-cta-consent",
        "presence": "div.fc-choice-dialog"
      },
      "domain": "origo.hu",
      "cookies": {
        "optIn": [
          {
            "name": "FCNEC",
            "value": "%5B%5B%22AKsRol_k06Um5W9IpBjIFW9eRDsjRFtq7VAwu4Y-ZcgfxP5wE1YvA2I254zUqCjHOfOu8kv_4lFhSizwYdX3WoQE96FGHCFUvlFJULLA6ytAfOzPbOgTCBP9nmNq0nIYwV1m9im8pUaOwNfssH6zO1V6EBy4L6bx4w%3D%3D%22%5D%2Cnull%2C%5B%5D%5D"
          }
        ],
        "optOut": [
          {
            "name": "FCCDCF",
            "value": "%5Bnull%2Cnull%2Cnull%2C%5B%22CPgbQkAPgbQkAEsABCHUCjCoAP_AAH_AAA6gHQpB7D7FbSFCyP55aLsAMAhXRkCEAqQAAASFAmABQAKQIBQCkkAQFAygBCACAAAgIAJBAQIMCAgACUEBQABAAAEEAAAABAAIIAAAgAEAAAAIAAACAIAAEAAIQAAAEAAAmQhAAIIACAAABAAAAAAAAAAAAAAAAgdCgHsLsVtIUJI_GkoswAgCFdGQIQCoAAAAIUCQAAAApAgBAKQQBAADKAEIAAAACAgAgEBAAgACAABQQFAAEAAAAAAAAAAAAggAACAAQAAAAAAAAIAgAAQAAhAAAAAAACJCEAAggAIAAAAAAAAAAAAAAAAAAACAAA.cqAADVgAAAA%22%2C%221~2052.2072.70.89.93.108.122.149.2202.162.167.196.2253.241.2299.259.2331.2357.311.317.323.2373.338.358.2415.415.440.449.2506.2526.482.486.494.495.2568.2571.2575.540.574.2624.2677.2707.817.827.2898.864.981.1031.1048.1051.1067.1095.1097.1127.1171.1201.1205.1211.1276.1301.1365.1415.1449.1570.1577.1616.1651.1716.1753.1765.1870.1878.1889.1917.1958.2012%22%2C%228BB76B67-7925-4F57-BFC5-31C47ABF23A9%22%5D%2Cnull%2Cnull%2C%5B%5D%5D"
          }
        ]
      },
      "id": "f236d4c4-1f2f-4b62-a4ec-5d9388d9150e"
    },
    {
      "click": {
        "optIn": "button.rodo-popup-agree",
        "presence": "div.rodo-popup-buttons"
      },
      "domain": "interia.pl",
      "cookies": {
        "optIn": [
          {
            "name": "cto_bundle",
            "value": "LBunHV9SeXV5T0JGRjcwT1d5QXZCM1psUW5UWDFrSU90aDhrbCUyQlROaGRTdVRiQ1JteUwxUWVGYnZjJTJGR0N4WXJ2d2hHOTBrVFA5ZkE0U21kS05IMFNXRDVRMGJyUnJTMkJPdlpZb0JmSE5tUml6MTRSaVJFZVIwbkU4TzlIbG0xMHZ4d1RZTW5WMjZscHN2Zjl4NG9BTWpaZ1hBJTNEJTNE"
          }
        ],
        "optOut": [
          {
            "name": "inplrd",
            "value": "{\"v\":\"4\",\"d\":1665039766996,\"tcf\":\"CPgbQkAPgbQkADnACAENCcCsAAAAAAAAAB5YI8Nd_X__bW9j-_5_aft0eY1P9_r37uQzDhfNk-8F3L_W_LwX52E7NF36pq4KmR4Eu1LBIQNlHMHUDUmwaokVrzHsak2cpyNKJ7JEknMZOydYGF9Pn1tjuYKY7_5_9_bx2D-t_9_-39T378Xf3_dp_2_-_vCfV599jfn9fV_789KP9_78v-_8__________3_7BHYAkw1biALsyxwZtAwigRAjCsJCqBQAQUAwtEFgA4OCnZWAT6whYAIBQhGBECHEFGDAIABBIAkIgAkCLBAIgCIBAACABEAhAAxMAgsALAwCAAEA0LFEKAAQJCDIgIjlMCAqBIKCWysQSgr0NMIA6zwAoNEbFQAIkkBFICAkLBwDBEgJWLJA0xRvkAIwQoBRKgAAAAA.YAAAAAAAAAAA\"}"
          }
        ]
      },
      "id": "ef9bacb9-d248-4129-baed-354a45277750"
    },
    {
      "click": {
        "optIn": "button#onetrust-accept-btn-handler",
        "presence": "div#onetrust-button-group"
      },
      "domain": "olx.ro",
      "cookies": {},
      "id": "2afae09c-b2a3-4e70-ab99-0e38d641352f"
    },
    {
      "click": {
        "optIn": "button",
        "presence": "div.fucking-eu-cookies"
      },
      "domain": "bazos.sk",
      "cookies": {
        "optIn": [
          {
            "name": "fucking-eu-cookies",
            "value": "1"
          }
        ]
      },
      "id": "5cb47b97-2d77-4301-af71-0ec0b4aa0e9c"
    },
    {
      "click": {
        "optIn": "button#L2AGLb",
        "optOut": "button#W0wltc",
        "presence": "div.spoKVd"
      },
      "domain": "google.ie",
      "cookies": {
        "optIn": [
          {
            "name": "CONSENT",
            "value": "PENDING"
          }
        ],
        "optOut": [
          {
            "name": "SOCS",
            "value": "CAESHAgBEhJnd3NfMjAyMjEwMTktMF9SQzQaAmVuIAEaBgiAlOeaBg"
          }
        ]
      },
      "id": "f65d0b22-54eb-48d1-8034-05ae1e42b59f"
    },
    {
      "click": {
        "optIn": "button#L2AGLb",
        "optOut": "button#W0wltc",
        "presence": "div.spoKVd"
      },
      "domain": "google.co.uk",
      "cookies": {
        "optIn": [
          {
            "name": "CONSENT",
            "value": "PENDING"
          }
        ],
        "optOut": [
          {
            "name": "SOCS",
            "value": "CAESHAgBEhJnd3NfMjAyMjEwMTktMF9SQzQaAmVuIAEaBgiAlOeaBg"
          }
        ]
      },
      "id": "bc0dffff-9534-4d3e-bb83-0a0d48a53023"
    },
    {
      "click": {
        "optIn": "button.cmp-consent-accept-btn",
        "presence": "div#notice"
      },
      "domain": "t-online.de",
      "cookies": {
        "optIn": [
          {
            "name": "euconsent-v2",
            "value": "CPgbQkAPgbQkAAGABCENCjCgAP_AAAAAACJwIpBVJCpNDWFAMHBdAJAgGYAU1sAUICQACBCAAyAFCAGA8IAA0QAAEAQAAAACAAAAgVABAAAAAABEAACAAAAEAQFkAAQAgAAIAAAAAAEQQgBQAAgAAAAAAAAIgAABAwQAkACQI4LGBUCAhIAQSgAAgIgBgIACAAMACEAYAAAAAAIAAIBAAgJEMIAAAAEAAABwiAIAIaAfYB-AHyATsEgTgAIAAqABkADkAHwAgABkADSAIgAigBMACeAG8AOYAfgBCACGgEQARIAlgBSgC3AGHAPsA_QCBgEUAI0AXMA2gBuAD0AHyATsAocBeYDBgGGgNZAcEA8cCEIEUggAUAc4C6AGQgQMAhcGgCACGgH2AfgB8gE7DIAQATAF5ioAQATAF5joFYAFQAMgAcgA-AEAAMgAaAA-gCIAIoATAAngBvADmAH4AQ0AiACJAEsAJgAUoAtwBhgDRgH2AfoBAwCKAEWALmAYoA2gBuAD0AIvATIAnYBQ4C8wGDAMNAZUAywBmYDiwHjgRSHADAAEAAXACgAOcAvQB5AD5AIQAXEAugBkIDTSEAsADIATAA3gClAH2ARQAuYBigDaAHoAeOQACgAIAHOAVkBdAEKCUBMABAAGQAOAAfACIAEwAQ0AiACJAFKALeAfYB-AFzAMUAbgA-QCLwF5gMsAhCSAAgAXKQJAAKgAZAA5AB8AIAAZAA0gCIAIoATAAngBSADmAH4AQ0AiACJAFKALcAaMA-wD9AIsAXMAxQBtADcAHoAReAnYBQ4C8wGGgMsAayA4IB44EIQIZgRSKABQALgDnAKyAeQCBgAA.f_gAAAAAAAAAv"
          }
        ]
      },
      "id": "52d4f423-db09-49d7-9c75-9a8e2a809c10"
    },
    {
      "click": {
        "optIn": "button.fc-cta-consent",
        "presence": "div.fc-footer-buttons-container"
      },
      "domain": "24chasa.bg",
      "cookies": {
        "optIn": [
          {
            "name": "FCNEC",
            "value": "%5B%5B%22AKsRol9wPbrrT0XxK2oBMiO6q7HB_AK0BUaXIwvIPlQgCmiJABJWLPfWmZ-Zwsc9_HyzD4Bi8r2QXuStu9BncawvOu1P735UQQho7830-bPSnLu9nZYgEbeAK5Gh9iony5ASGp7_2O_ojpD4iXZgQ5Ee7NQaZNMUhA%3D%3D%22%5D%2Cnull%2C%5B%5D%5D"
          }
        ],
        "optOut": [
          {
            "name": "FCCDCF",
            "value": "%5Bnull%2Cnull%2Cnull%2C%5B%22CPgbQkAPgbQkAEsABCBGCjCgAAAAAAAAAAIwAAAOhQD2F2K2kKEkfjSUWYAQBCujIEIBUAAAAECBIAAAAUgQAgFIIAgAAlACAAAAABAQAQCAgAQABAAAoACgACAAAAAAAAAAAAQQAABAAIAAAAAAAAEAQAAAAAQAAAAAAABEhCAAQQAEAAAAAAAAAAAAAAAAAAABAAA.YAAAAAAAAAA%22%2C%221~%22%2C%22FA11CE3A-809E-4B87-BFDE-13E9DE22F419%22%5D%2Cnull%2Cnull%2C%5B%5D%5D"
          }
        ]
      },
      "id": "97ba1ec3-c8e7-45a0-845f-c732b71bd213"
    },
    {
      "click": {
        "optIn": "button#CybotCookiebotDialogBodyLevelButtonLevelOptinAllowAll",
        "optOut": "button#CybotCookiebotDialogBodyButtonDecline",
        "presence": "div#CybotCookiebotDialogBodyButtons"
      },
      "domain": "ekstrabladet.dk",
      "cookies": {
        "optIn": [
          {
            "name": "cto_bundle",
            "value": "hllas19iN3FWU0pJYVF6JTJGWEVVRE5kJTJGbDFUSXlOMmsyR1hrYW5nVjdoMG1vQ1k4dFZMSW1sSXlIVHpWQ2ozaEolMkI3Yndid2doUERKMVN1c3R1M3VRNSUyQlRNdnFnaTJkRkJ0V0J5VVhQcU1WeXdMbXBUOVdBc3JTWklBVHNTSXZmZWlNN0o5ZTBWSUdwd1BldkE1eXhNeU9HSlZYQSUzRCUzRA"
          }
        ],
        "optOut": [
          {
            "name": "CookieConsent",
            "value": "{stamp:%27QmpmezEASR/DS4/lr1mawVaNO945EW6sk0Hi0cjL1CFS1A36t8Os1Q==%27%2Cnecessary:true%2Cpreferences:false%2Cstatistics:false%2Cmarketing:false%2Cver:3%2Cutc:1665042549753%2Ciab2:%27CPgbQkAPgbQkACGABBENCjCgAAAAAE_AAAAAAAASCAJMNW4gC7EscCbQMIoEQIwrCQqgUAEFAMLRAYAODgp2VgE-sIEACAUARgRAhxBRgQCAAACAJCIAJAiwQCIAiAQAAgARCIQAEDAIKACwMAgABANAxRCgAECQgyICIpTAgIgSCAlsqEEoK5DTCAOssAKDRGxUACJAABSAAJCwcAwRICViwQJMUb5ACMEKAUSoVoAA.YAAAAAAAAAAA%27%2Cgacm:%271~%27%2Cregion:%27ro%27}"
          }
        ]
      },
      "id": "7c2c6827-7d60-49a5-b4c1-877ba7fcd2e7"
    },
    {
      "click": {
        "optIn": "button.iubenda-cs-accept-btn",
        "presence": "div.iubenda-cs-opt-group-consent"
      },
      "domain": "repubblica.it",
      "cookies": {
        "optOut": [
          {
            "name": "euconsent-v2",
            "value": "CPgbQkAPgbQkAB7EVCITCjCgAAAAAAAAAAAAAAAQpgFgA4ACWAZ8BHgCVwGCAMfAdsA7kB4IEKQCQkFgABAAC4AKAAqABkADkAHgAgABgADKAGgAagA8gCGAIoATAAngBVADeAHMAPQAfgBCQCGAIkARwAlgBNAClAFuAMMAZAAywBsgDvgHsAfEA-wD9gH-AgYBFICLgIxARoBHACUgFBAKeAVcAuYBogDWAG0ANwAcQA9AB8gEOgIhASIAmUBOwChwFIgKaAWKAtABbAC5AF3gLzAYMAw2BkYGSAMnAZcAzkBnwDSIGsAayA28BuoDggHEQOTA5QBy4DxwHtAQhghcCF4EOQIegQ_AiGBFICPoEfw0B0ALgAhgBkADLAGzAPsA_ACAAEFAIwAU8Aq8BaAFpANYAdUA-QCHQETAIqASIAnYBSIC5AGRgMnAZyAzwBnwDlAI_iIC4AhgBkADLAGzAPsA_ACAAEYAKeAVcA1gB1QD5AIdASIAnYBSIC5AGRgMnAZyAz4BygEfxUBQACgAQwAmABcAEcAMsAjgBV4C0ALSAtgBcgC8wGRgM5AZ4Az4BuQDlAIXgR_GQEwAhgBMAEcAMsAjgBVwCtgJOAWiAtgBcgC8wGRgM5AZ4Az4BygELwI_joNwAC4AKAAqABkADkAHwAgABdADAAMoAaABqADwAH0AQwBFACYAE8AKsAXABdADEAGYAN4AcwA9AB-gEMARIAlgBMACaAFGAKUAWIAt4BhAGHAMgAygBogDZAHeAPaAfYB-gD_AIGARSAiwCMQEcAR0AlIBQQCngFXALFAWgBaYC5gLrAXkBegDFAG0ANwAcQA5wB1AD0AH2AQ6AiEBFQCLwEiAJUATIAnYBQ4CmgFWALFAWUAtgBcAC5AF2gLvAXmAvoBgwDDQGPQMjAyQBk4DKgGWAMuAZmAzkBnwDRIGkAaSA1UBrADbwG6gOIAcXA5MDlAHLgPHAe0A-sCAIEGgIXwQ5BDoCHoEUgI7AR9Aj-QghgALAAoABkAFwAMQAagBDACYAFMAKoAXAAxABmADeAHoARwApQBYgDCAGUAO8AfYA_wCKAEcAJSAUEAp4BV4C0ALSAXMAxQBtADnAHUAPQAiEBIgCTgEqAKaAVYAsUBZQC0QFsALgAXIAu0BkYDJwGcgM8AZ8A0QBpIDVQHAAOIAcoA8cCFAELwIdAQ9Aj6BH8lA_AAQAAsACgAGQAOAAfgBgAGIAPAAiABMACqAFwAMQAZoBDAESAI4AUYApQBbgDCAGUANkAd8A-wD8AI4AU8Aq8BaAFpgLmAuoBigDcAHUAPkAfYBDoCJgEVAIvASIAsUBZQC2AF2gLzAZGAycBlgDOQGeAM-AaQA1gBt4DgAHtAQBAgeBCECF4ENQIegRZAj-UgqgALgAoACoAGQAOQAfACCAGAAZQA0ADUAHkAQwBFACYAE8AKQAVQAxABmADmAH6AQwBEgCjAFKALEAW4AwoBkAGUANEAbIA74B9gH6ARYAjEBHAEdAJSAUEAq4BWwC5gF5AMUAbQA3AB6AD7AIdARMAi8BIgCTgE7AKHAVYAsUBaAC2AFwALkAXaAvMBfQDDYGRgZIAycBlgDLgGcgM8AZ9A0gDSYGsAayA28BuoDgoHJgcoA5cB4oDxwHtAQhAheBDMCHQEPQIgARSAjsBH8"
          }
        ]
      },
      "id": "5c862324-6a7c-43d8-ae34-47c5e7d355f6"
    },
    {
      "click": {
        "optIn": "button#didomi-notice-agree-button",
        "presence": "div#buttons"
      },
      "domain": "independent.ie",
      "cookies": {
        "optOut": [
          {
            "name": "euconsent-v2",
            "value": "CPgbQkAPgbQkAAHABBENCjCgAAAAAAAAAAAAAAAAAACBoAMAAQSCFQAYAAgkEIgAwABBIIZABgACCQQA.YAAAAAAAAAAA"
          }
        ]
      },
      "id": "7cab9873-2ff9-43c8-a011-5bc1df3c86fe"
    },
    {
      "click": {
        "optIn": "button.css-pp-ok",
        "presence": "div.css-pp-box"
      },
      "domain": "dagbladet.no",
      "cookies": {},
      "id": "ebbaf3a6-10bb-4cd3-8294-5b095984e21a"
    },
    {
      "click": {
        "optIn": "button#L2AGLb",
        "optOut": "button#W0wltc",
        "presence": "div.spoKVd"
      },
      "domain": "google.pl",
      "cookies": {
        "optIn": [
          {
            "name": "CONSENT",
            "value": "PENDING"
          }
        ],
        "optOut": [
          {
            "name": "SOCS",
            "value": "CAESHAgBEhJnd3NfMjAyMjEwMDMtMF9SQzEaAnJvIAEaBgiAtfiZBg"
          }
        ]
      },
      "id": "078462db-30bb-43d5-8016-53513dbd9020"
    },
    {
      "click": {
        "optIn": "button#didomi-notice-agree-button",
        "optOut": "button#didomi-notice-disagree-button",
        "presence": "div.didomi-popup-view"
      },
      "domain": "willhaben.at",
      "cookies": {},
      "id": "b783a182-7f67-4b62-929c-5d9be04e9cb9"
    },
    {
      "click": {
        "optIn": "button.fc-cta-consent",
        "presence": "div.fc-choice-dialog"
      },
      "domain": "blitz.bg",
      "cookies": {
        "optIn": [
          {
            "name": "FCNEC",
            "value": "%5B%5B%22AKsRol-bQbYlqinAT-OoNPKXWSy-wKAi4Q9zS-Pqvu9He7xaNYGAkWcM72hhx35gJHGcxbw4ZxpGWfUKdFLm8nAqw-hO3QSDHVlEdUcEYYQIJpn4H26of13iJ1NTrQcwrOnYCF_oKUZSnVQrH5n8XY0y8rS6n4_myQ%3D%3D%22%5D%2Cnull%2C%5B%5D%5D"
          }
        ],
        "optOut": [
          {
            "name": "FCCDCF",
            "value": "%5Bnull%2Cnull%2Cnull%2C%5B%22CPgbQkAPgbQkAEsABCBGCjCgAAAAAAAAAAIwAAAPaQD2F2K2kKEkfjaUWYIQBCujKEIBUBAEAEKBIAAAAUgQAgFIIAgABlACEAAAABAQAQCAgAQABAAAoICgACAAAAAQAAAAAAQQAABAAIAAACAAAAEAQAAAAAQAAAAAAABEhCAAQSQEAAAAAAAAAAAAAAAAAAABAAAAAAAAAIAA.YAAAAAAAAAA%22%2C%221~%22%2C%226C13DA30-0357-4AD8-8594-DBD146A8DF46%22%5D%2Cnull%2Cnull%2C%5B%5D%5D"
          }
        ]
      },
      "id": "7850dc20-f121-417b-9eb0-d91a0a8d6a8c"
    },
    {
      "click": {
        "optIn": "button#didomi-notice-agree-button",
        "presence": "div#buttons"
      },
      "domain": "leboncoin.fr",
      "cookies": {
        "optOut": [
          {
            "name": "atauthority",
            "value": "%7B%22name%22%3A%22atauthority%22%2C%22val%22%3A%7B%22authority_name%22%3A%22cnil%22%2C%22visitor_mode%22%3A%22exempt%22%7D%2C%22options%22%3A%7B%22end%22%3A%222023-11-05T09%3A17%3A06.829Z%22%2C%22path%22%3A%22%2F%22%7D%7D"
          }
        ]
      },
      "id": "ca9fef29-efe4-4f88-8b18-6c8d87414ffe"
    },
    {
      "click": {
        "optIn": "button.fc-cta-consent",
        "optOut": "button.fc-cta-do-not-consent",
        "presence": "div.fc-footer-buttons-container"
      },
      "domain": "ilmeteo.it",
      "cookies": {
        "optIn": [
          {
            "name": "cto_bundle",
            "value": "vnzlCV9BeVNocGZHbWZaJTJCajMxUnJpJTJGN2NISUZWZDV4R3dBTWZ4c3JSTVIlMkI1N3VFd1lyaWU5SExMJTJGMGxUR2lJU1Q0aTVJcmNubW5JalBmJTJGQnVWQiUyRndmZnRKcFhWVno0Ym9OTzJud2l4JTJGUmdoQTJCVkpkbW02TGkzWHZTZHclMkJNYUdDQnpNNWZnJTJGdTV1bU13OExyJTJCTFBtNUhJZyUzRCUzRA"
          }
        ],
        "optOut": [
          {
            "name": "FCCDCF",
            "value": "%5Bnull%2Cnull%2Cnull%2C%5B%22CPgbQkAPgbQkAEsABBITCjCgAAAAAH_AABCYAAAO9QD2F2K2kKEkfjSUeYAQBCujIEIBUAAAAEKBIAAAAUgQAgFIIAgABlACEAAAABAQAQCAgAQABAAAoICgACAAAAAAAAAQAAQQAABAAIAAAAAAAAEAQAAAAAQAAAAAAAhEhCAAQQAEIAAAAAAAAAAAAAAAAAABAAAAEAA%22%2C%221~%22%2C%22A83BB90B-53A8-400D-8DAA-F4EF44E9B970%22%5D%2Cnull%2Cnull%2C%5B%5D%5D"
          }
        ]
      },
      "id": "71d0715b-3e8e-4077-969e-7b7722f78910"
    },
    {
      "click": {
        "optIn": "button#didomi-notice-agree-button",
        "presence": "div#buttons"
      },
      "domain": "telegraaf.nl",
      "cookies": {
        "optOut": [
          {
            "name": "euconsent-v2",
            "value": "CPgbQkAPgbQkAAHABBENCjCgAAAAAAAAAAAAAAAAAAEhoAMAAQSCEQAYAAgkESgAwABBIIVABgACCQRSADAAEEgh0AGAAIJBEIAMAAQSCCQAYAAgkEMgAwABBIIA.YAAAAAAAAAAA"
          }
        ]
      },
      "id": "7b16cf99-61ba-4f32-af17-d97c4fe241a1"
    },
    {
      "click": {
        "optIn": "button.fc-cta-consent",
        "presence": "div.fc-footer-buttons"
      },
      "domain": "abola.pt",
      "cookies": {
        "optOut": [
          {
            "name": "FCCDCF",
            "value": "%5Bnull%2Cnull%2Cnull%2C%5B%22CPgbQkAPgbQkAEsABCPTCjCgAAAAAAAAAB6YAAARbY7-N262v7O8fnfUebo0Rq-r-Uv1cBmHCOLRo4BOX8t-VgH-sJ2ALt0aVgRMjxJZqQCQgISAJOICpNi0RKqWiGQQAkxRAaQQ2DJILYy8sCgIJofFxKCsAUzy9zcSM7zklvx3Tf9v7lut77r_iZet8HfpfG39xbbNtba8AJzwcE4ZqSVr16d-d__pmclAAA%22%2C%221~%22%2C%22862FB90F-02B3-4D6C-AFCB-6D85B90158EA%22%5D%2Cnull%2Cnull%2C%5B%5D%5D"
          }
        ]
      },
      "id": "8e8f6719-0350-4310-8cc1-c00bb51b72b0"
    },
    {
      "click": {
        "optIn": "button#onetrust-accept-btn-handler",
        "presence": "div#onetrust-button-group"
      },
      "domain": "gsp.ro",
      "cookies": {
        "optOut": [
          {
            "name": "eupubconsent-v2",
            "value": "CPgcjsWPgcjsWAcABBENCjCgAAAAAH_AAChQJBNf_X__b2_j-_5_f_t0eY1P9_7__-0zjhfdl-8N3f_X_L8X52M7vF36tq4KuR4Eu3LBIUdlHOHcTUmw6okVryPsbk2cr7NKJ7PEmnMbOydYGH9_n1_z-ZKY7___f_7z_v-v___3____7-3f3__5___-__e_V__9zfn9_____9vP___9v-_9__________3_798EggCTDVuIAuxLHAm2jCKBECMKwkOoFABRQDC0QGEDq4KdlcBPrCBAAgFAEYEQIcQUYMAgAAAgCQiICQI8EAiAIgEAAIAFQiEABGwCCgAsDAIABQDQsUYoAhAkIMiAiKUwICJEgoJ7KhBKDvQ0whDrLACg0f8VCAiUAIVgRCQsHIcESAl4skCzFG-QAjBCgFEqFaAA.YAAAD_gAAAAA"
          }
        ]
      },
      "id": "13353fdd-5cd9-4254-b70b-c59e45077a89"
    },
    {
      "click": {
        "optIn": "button#didomi-notice-agree-button",
        "presence": "div#buttons"
      },
      "domain": "as.com",
      "cookies": {
        "optOut": [
          {
            "name": "euconsent-v2",
            "value": "CPgbQkAPgbQkAAHABBENCjCgAAAAAAAAAAAAAAAAAAEkoAMAAQSCDQAYAAgkEKgAwABBIIpABgACCQQ6ADAAEEgiEAGAAIJBBIAMAAQSCEQAYAAgkEMgAwABBIIA.YAAAAAAAAAAA"
          }
        ]
      },
      "id": "9c4c729b-0ecb-4d9c-b526-c36ad0ca4fee"
    },
    {
      "click": {
        "optIn": "button.cookie-close",
        "presence": "div#cookiesBar"
      },
      "domain": "olx.ua",
      "cookies": {
        "optIn": [
          {
            "name": "cookieBarSeen",
            "value": "true"
          }
        ]
      },
      "id": "9944d588-486e-4f01-a5b9-17d1e9cc744a"
    },
    {
      "click": {
        "optIn": "button#gdpr-banner-accept",
        "optOut": "button#gdpr-banner-decline",
        "presence": "div.gdpr-banner-actions"
      },
      "domain": "ebay.co.uk",
      "cookies": {},
      "id": "254c02f7-4f33-41f7-8bda-56404568a8e2"
    },
    {
      "click": {
        "optIn": "button#L2AGLb",
        "optOut": "button#W0wltc",
        "presence": "div.spoKVd"
      },
      "domain": "google.com.mx",
      "cookies": {
        "optIn": [
          {
            "name": "CONSENT",
            "value": "PENDING"
          }
        ],
        "optOut": [
          {
            "name": "SOCS",
            "value": "CAESHAgBEhJnd3NfMjAyMjEwMDMtMF9SQzEaAnJvIAEaBgiAtfiZBg"
          }
        ]
      },
      "id": "bd70d2fa-317e-4ffb-92d7-8426d25f2154"
    },
    {
      "click": {
        "optIn": "button#gdpr-banner-accept",
        "presence": "div.jsx-1433135011"
      },
      "domain": "ebay-kleinanzeigen.de",
      "cookies": {
        "optIn": [
          {
            "name": "cto_bundle",
            "value": "74wav19heDMyZkEyQlhqdVlDMWhRa1pLWUJhSjAyQjVCb3FrNUtQak5DJTJGTDBLcjRRQ1lmdHl2NEZyJTJCdFdta2FCczdnTjI2blh4STNVZWswRmJoWXEyUzlOczdCcE54WXljcWRRNnhDZFNvQW4yQmQyZEphZ2FvZ3J6JTJCU09jWkFrZE1uQXZaQktmZTg5MVp0VUowazZLQlJidXclM0QlM0Q"
          }
        ],
        "optOut": [
          {
            "name": "ekConsentTcf2",
            "value": "{%22customVersion%22:3%2C%22encodedConsentString%22:%22CPgcl9uPgcl9uE1ABADECQCgAAAAAAAAAAYgIUwMAAcABLACmAH6AiwCMAFGALaAYAAz4BrwDpAHkASKAlcBMgCrAFhALqAXeAvoBggDBgGJAMvAZ8A0YBpIDTQGqwNoA2kBuYDggHHgOUAc2A50Bz4DtgHcgO8AeCA-2B-AH4wP1A_YCCIEFAIPAQpAAAASUgAwABBGIlABgACCMRCADAAEEYh0AGAAIIxDIAMAAQRiFQAYAAgjEIgAwABBGINABgACCMQSADAAEEYg%22%2C%22googleConsentGiven%22:false%2C%22consentInterpretation%22:{%22googleAdvertisingFeaturesAllowed%22:false%2C%22googleAnalyticsAllowed%22:false%2C%22infonlineAllowed%22:false%2C%22theAdexAllowed%22:false}}"
          }
        ]
      },
      "id": "dbc0dde3-600b-40ab-ab8b-b07e3e3c7af8"
    },
    {
      "click": {
        "optIn": "button#didomi-notice-agree-button",
        "presence": "div#buttons"
      },
      "domain": "slobodnadalmacija.hr",
      "cookies": {
        "optOut": [
          {
            "name": "euconsent-v2",
            "value": "CPgejgAPgejgAAHABBENCjCgAAAAAAAAAAAAAAAAAAAA.YAAAAAAAAAAA"
          }
        ]
      },
      "id": "d46017a3-bd38-41d2-9e2c-3c0a0b729e99"
    }
  ]
}
